AUTHOR.txt
CHANGES.txt
LICENSE.txt
README.txt
bootstrap.py
buildout.cfg
setup.py
src/z3c/__init__.py
src/z3c.formwidget.ckeditor.egg-info/PKG-INFO
src/z3c.formwidget.ckeditor.egg-info/SOURCES.txt
src/z3c.formwidget.ckeditor.egg-info/dependency_links.txt
src/z3c.formwidget.ckeditor.egg-info/namespace_packages.txt
src/z3c.formwidget.ckeditor.egg-info/not-zip-safe
src/z3c.formwidget.ckeditor.egg-info/requires.txt
src/z3c.formwidget.ckeditor.egg-info/top_level.txt
src/z3c/formwidget/__init__.py
src/z3c/formwidget/ckeditor/README.txt
src/z3c/formwidget/ckeditor/__init__.py
src/z3c/formwidget/ckeditor/ckeditor-js.zcml
src/z3c/formwidget/ckeditor/ckeditor.py
src/z3c/formwidget/ckeditor/ckeditor_input.pt
src/z3c/formwidget/ckeditor/configure.zcml
src/z3c/formwidget/ckeditor/interfaces.py
src/z3c/formwidget/ckeditor/richtext.py
src/z3c/formwidget/ckeditor/tests.py
src/z3c/formwidget/ckeditor/ckeditor-js/.htaccess
src/z3c/formwidget/ckeditor/ckeditor-js/CHANGES.html
src/z3c/formwidget/ckeditor/ckeditor-js/INSTALL.html
src/z3c/formwidget/ckeditor/ckeditor-js/LICENSE.html
src/z3c/formwidget/ckeditor/ckeditor-js/ckeditor.js
src/z3c/formwidget/ckeditor/ckeditor-js/ckeditor.pack
src/z3c/formwidget/ckeditor/ckeditor-js/ckeditor_basic.js
src/z3c/formwidget/ckeditor/ckeditor-js/ckeditor_basic_source.js
src/z3c/formwidget/ckeditor/ckeditor-js/ckeditor_source.js
src/z3c/formwidget/ckeditor/ckeditor-js/config.js
src/z3c/formwidget/ckeditor/ckeditor-js/contents.css
src/z3c/formwidget/ckeditor/ckeditor-js/_samples/ajax.html
src/z3c/formwidget/ckeditor/ckeditor-js/_samples/api.html
src/z3c/formwidget/ckeditor/ckeditor-js/_samples/api_dialog.html
src/z3c/formwidget/ckeditor/ckeditor-js/_samples/autogrow.html
src/z3c/formwidget/ckeditor/ckeditor-js/_samples/divreplace.html
src/z3c/formwidget/ckeditor/ckeditor-js/_samples/enterkey.html
src/z3c/formwidget/ckeditor/ckeditor-js/_samples/fullpage.html
src/z3c/formwidget/ckeditor/ckeditor-js/_samples/index.html
src/z3c/formwidget/ckeditor/ckeditor-js/_samples/jqueryadapter.html
src/z3c/formwidget/ckeditor/ckeditor-js/_samples/output_for_flash.html
src/z3c/formwidget/ckeditor/ckeditor-js/_samples/output_html.html
src/z3c/formwidget/ckeditor/ckeditor-js/_samples/output_xhtml.html
src/z3c/formwidget/ckeditor/ckeditor-js/_samples/placeholder.html
