Metadata-Version: 1.0
Name: z3c.formwidget.ckeditor
Version: 1.1.0
Summary: A CKEditor widget for text fields using z3c.form
Home-page: http://pypi.python.org/pypi/z3c.formwidget.ckeditor
Author: Stephan Richter and the Zope Community
Author-email: zope-dev@zope.org
License: ZPL 2.1
Keywords: zope3 form widget ckeditor text
Platform: UNKNOWN
Classifier: Development Status :: 4 - Beta
Classifier: Environment :: Web Environment
Classifier: Intended Audience :: Developers
Classifier: License :: OSI Approved :: Zope Public License
Classifier: Programming Language :: Python
Classifier: Natural Language :: English
Classifier: Operating System :: OS Independent
Classifier: Topic :: Internet :: WWW/HTTP
Classifier: Framework :: Zope3
